pylexique/Lexique383/Lexique383.txt
pylexique/Lexique383/RELEASE NOTES-Lexique.txt
pylexique/__init__.py
pylexique/cli.py
pylexique/errors/errors.json
pylexique/errors/length_errors.json
pylexique/errors/value_errors.json
pylexique/py.typed
pylexique/pylexique.py
pylexique/utils.py
tests/__init__.py
tests/test_pylexique.py
pylexique-1.5.1.dist-info/LICENSE
pylexique-1.5.1.dist-info/METADATA
pylexique-1.5.1.dist-info/WHEEL
pylexique-1.5.1.dist-info/entry_points.txt
pylexique-1.5.1.dist-info/RECORD
