Metadata-Version: 2.1
Name: pylexique
Version: 1.5.1
Summary: Pylexique is a Python wrapper around Lexique383
Home-page: https://github.com/SekouDiaoNlp/pylexique
License: MIT
Keywords: pylexique
Author: SekouDiaoNlp
Author-email: diao.sekou.nlp@gmail.com
Maintainer: SekouDiaoNlp
Maintainer-email: diao.sekou.nlp@gmail.com
Requires-Python: >=3.8,<4
Classifier: Development Status :: 5 - Production/Stable
Classifier: Intended Audience :: Developers
Classifier: Intended Audience :: Education
Classifier: Intended Audience :: End Users/Desktop
Classifier: Intended Audience :: Science/Research
Classifier: License :: OSI Approved :: MIT License
Classifier: Natural Language :: English
Classifier: Natural Language :: French
Classifier: Operating System :: OS Independent
Classifier: Programming Language :: Python :: 3
Classifier: Programming Language :: Python :: 3.8
Classifier: Programming Language :: Python :: 3.9
Classifier: Programming Language :: Python :: 3.10
Classifier: Programming Language :: Python :: 3.11
Classifier: Programming Language :: Python :: 3.6
Classifier: Programming Language :: Python :: 3.7
Classifier: Topic :: Education
Classifier: Topic :: Scientific/Engineering :: Artificial Intelligence
Classifier: Topic :: Software Development :: Libraries :: Python Modules
Classifier: Topic :: Utilities
Requires-Dist: click (>=8.0.3)
Requires-Dist: colorama
Requires-Dist: dataclasses (>=0.6) ; python_version < "3.7"
Requires-Dist: joblib (>=1.0.1,<2.0.0)
Requires-Dist: pandas (>=2.0.1,<3.0.0)
Requires-Dist: tqdm
Project-URL: Documentation, https://pylexique.readthedocs.io/en/latest/readme.html
Project-URL: Repository, https://github.com/SekouDiaoNlp/pylexique
